rotom/__init__.py
rotom/__main__.py
rotom/app.py
rotom/modules/__init__.py
rotom/modules/common/__init__.py
rotom/modules/common/app.py
rotom/modules/common/hash.py
rotom/modules/common/path.py
rotom-0.0.2.dist-info/METADATA
rotom-0.0.2.dist-info/WHEEL
rotom-0.0.2.dist-info/entry_points.txt
rotom-0.0.2.dist-info/top_level.txt
rotom-0.0.2.dist-info/RECORD
