Metadata-Version: 2.1
Name: rotom
Version: 0.0.2
Summary: rotom
Home-page: https://github.com/NgHoangDat/rotom.git
Download-URL: https://github.com/NgHoangDat/rotom/archive/v0.0.2.tar.gz
Author: nghoangdat
Author-email: 18.hoang.dat.12@gmail.com
Classifier: Programming Language :: Python :: 3
Classifier: License :: OSI Approved :: MIT License
Classifier: Operating System :: OS Independent
Requires-Python: >=3.6
Requires-Dist: cowsay
Requires-Dist: mousse
Requires-Dist: typer
Provides-Extra: all
Provides-Extra: common
